{
    "asset": {
        "format": "jpg",
        "id": "d810e04653df49b2ebc7a85cdeb6cc87",
        "name": "20211203-145649.jpg",
        "path": "file:D:/My_programing/Dobot_python/assets/anns/20211203-145649.jpg",
        "size": {
            "width": 1280,
            "height": 960
        },
        "state": 2,
        "type": 1
    },
    "regions": [
        {
            "id": "SogpWa-mm",
            "type": "POLYGON",
            "tags": [
                "dai"
            ],
            "boundingBox": {
                "height": 299.73799126637556,
                "width": 679.3120393120394,
                "left": 55.74119574119574,
                "top": 13.624454148471616
            },
            "points": [
                {
                    "x": 696.2653562653562,
                    "y": 13.624454148471616
                },
                {
                    "x": 675.2989352989354,
                    "y": 17.816593886462883
                },
                {
                    "x": 672.1539721539722,
                    "y": 30.393013100436683
                },
                {
                    "x": 669.009009009009,
                    "y": 52.40174672489083
                },
                {
                    "x": 669.009009009009,
                    "y": 57.64192139737991
                },
                {
                    "x": 653.2841932841933,
                    "y": 63.930131004366814
                },
                {
                    "x": 645.9459459459459,
                    "y": 70.21834061135371
                },
                {
                    "x": 634.4144144144144,
                    "y": 70.21834061135371
                },
                {
                    "x": 618.6895986895987,
                    "y": 46.11353711790393
                },
                {
                    "x": 600.8681408681409,
                    "y": 46.11353711790393
                },
                {
                    "x": 588.2882882882883,
                    "y": 52.40174672489083
                },
                {
                    "x": 569.4185094185094,
                    "y": 61.83406113537118
                },
                {
                    "x": 561.0319410319411,
                    "y": 49.25764192139738
                },
                {
                    "x": 523.2923832923833,
                    "y": 57.64192139737991
                },
                {
                    "x": 485.55282555282554,
                    "y": 68.12227074235808
                },
                {
                    "x": 485.55282555282554,
                    "y": 75.4585152838428
                },
                {
                    "x": 475.06961506961505,
                    "y": 79.65065502183405
                },
                {
                    "x": 470.8763308763309,
                    "y": 71.26637554585153
                },
                {
                    "x": 455.1515151515152,
                    "y": 75.4585152838428
                },
                {
                    "x": 442.57166257166256,
                    "y": 82.79475982532752
                },
                {
                    "x": 180.4914004914005,
                    "y": 163.4934497816594
                },
                {
                    "x": 81.94922194922195,
                    "y": 190.74235807860262
                },
                {
                    "x": 73.56265356265357,
                    "y": 189.6943231441048
                },
                {
                    "x": 63.07944307944308,
                    "y": 200.17467248908298
                },
                {
                    "x": 57.83783783783784,
                    "y": 206.46288209606988
                },
                {
                    "x": 55.74119574119574,
                    "y": 223.23144104803492
                },
                {
                    "x": 55.74119574119574,
                    "y": 233.7117903930131
                },
                {
                    "x": 64.12776412776412,
                    "y": 243.14410480349346
                },
                {
                    "x": 60.98280098280098,
                    "y": 255.72052401746726
                },
                {
                    "x": 56.78951678951679,
                    "y": 267.2489082969432
                },
                {
                    "x": 62.03112203112203,
                    "y": 277.7292576419214
                },
                {
                    "x": 73.56265356265357,
                    "y": 291.353711790393
                },
                {
                    "x": 79.85257985257985,
                    "y": 297.6419213973799
                },
                {
                    "x": 90.33579033579034,
                    "y": 301.8340611353712
                },
                {
                    "x": 101.86732186732186,
                    "y": 301.8340611353712
                },
                {
                    "x": 117.59213759213759,
                    "y": 313.3624454148472
                },
                {
                    "x": 134.36527436527436,
                    "y": 307.07423580786025
                },
                {
                    "x": 500.22932022932025,
                    "y": 189.6943231441048
                },
                {
                    "x": 510.71253071253074,
                    "y": 185.50218340611355
                },
                {
                    "x": 519.0990990990991,
                    "y": 175.02183406113537
                },
                {
                    "x": 521.1957411957412,
                    "y": 187.59825327510916
                },
                {
                    "x": 525.3890253890254,
                    "y": 194.93449781659388
                },
                {
                    "x": 564.1769041769041,
                    "y": 182.35807860262008
                },
                {
                    "x": 559.98361998362,
                    "y": 189.6943231441048
                },
                {
                    "x": 553.6936936936937,
                    "y": 200.17467248908298
                },
                {
                    "x": 561.0319410319411,
                    "y": 209.6069868995633
                },
                {
                    "x": 574.6601146601147,
                    "y": 211.70305676855895
                },
                {
                    "x": 601.9164619164619,
                    "y": 204.36681222707423
                },
                {
                    "x": 617.6412776412776,
                    "y": 197.03056768558952
                },
                {
                    "x": 628.1244881244882,
                    "y": 189.6943231441048
                },
                {
                    "x": 634.4144144144144,
                    "y": 180.26200873362444
                },
                {
                    "x": 623.931203931204,
                    "y": 150.9170305676856
                },
                {
                    "x": 620.7862407862408,
                    "y": 144.6288209606987
                },
                {
                    "x": 648.042588042588,
                    "y": 134.14847161572052
                },
                {
                    "x": 648.042588042588,
                    "y": 117.37991266375546
                },
                {
                    "x": 642.8009828009828,
                    "y": 103.75545851528385
                },
                {
                    "x": 663.7674037674037,
                    "y": 97.46724890829694
                },
                {
                    "x": 673.2022932022932,
                    "y": 98.51528384279476
                },
                {
                    "x": 698.3619983619984,
                    "y": 139.3886462882096
                },
                {
                    "x": 719.3284193284194,
                    "y": 139.3886462882096
                },
                {
                    "x": 719.3284193284194,
                    "y": 126.8122270742358
                },
                {
                    "x": 718.2800982800983,
                    "y": 104.80349344978166
                },
                {
                    "x": 718.2800982800983,
                    "y": 90.13100436681222
                },
                {
                    "x": 731.9082719082719,
                    "y": 83.84279475982532
                },
                {
                    "x": 735.0532350532351,
                    "y": 64.97816593886463
                },
                {
                    "x": 727.7149877149877,
                    "y": 57.64192139737991
                },
                {
                    "x": 713.038493038493,
                    "y": 61.83406113537118
                }
            ]
        },
        {
            "id": "Mh5S1fh2V",
            "type": "POLYGON",
            "tags": [
                "pen2"
            ],
            "boundingBox": {
                "height": 209.6069868995633,
                "width": 334.4144144144144,
                "left": 702.5552825552826,
                "top": 149.86899563318778
            },
            "points": [
                {
                    "x": 1036.969696969697,
                    "y": 319.65065502183404
                },
                {
                    "x": 868.1900081900081,
                    "y": 225.32751091703057
                },
                {
                    "x": 865.0450450450451,
                    "y": 226.3755458515284
                },
                {
                    "x": 721.4250614250615,
                    "y": 149.86899563318778
                },
                {
                    "x": 702.5552825552826,
                    "y": 181.31004366812226
                },
                {
                    "x": 843.030303030303,
                    "y": 257.8165938864629
                },
                {
                    "x": 843.030303030303,
                    "y": 265.1528384279476
                },
                {
                    "x": 1011.8099918099919,
                    "y": 359.4759825327511
                },
                {
                    "x": 1023.3415233415234,
                    "y": 352.1397379912664
                },
                {
                    "x": 1030.6797706797706,
                    "y": 329.0829694323144
                }
            ]
        },
        {
            "id": "be_Otd3eT",
            "type": "POLYGON",
            "tags": [
                "jyuc_g"
            ],
            "boundingBox": {
                "height": 386.72489082969435,
                "width": 625.8476658476659,
                "left": 618.6895986895987,
                "top": 248.38427947598254
            },
            "points": [
                {
                    "x": 1243.4889434889435,
                    "y": 528.2096069868995
                },
                {
                    "x": 774.8894348894349,
                    "y": 292.4017467248908
                },
                {
                    "x": 673.2022932022932,
                    "y": 248.38427947598254
                },
                {
                    "x": 662.7190827190827,
                    "y": 263.05676855895194
                },
                {
                    "x": 641.7526617526618,
                    "y": 298.68995633187774
                },
                {
                    "x": 627.076167076167,
                    "y": 334.3231441048035
                },
                {
                    "x": 618.6895986895987,
                    "y": 356.33187772925766
                },
                {
                    "x": 1184.7829647829649,
                    "y": 635.1091703056769
                },
                {
                    "x": 1207.846027846028,
                    "y": 618.3406113537118
                },
                {
                    "x": 1224.6191646191646,
                    "y": 596.3318777292576
                },
                {
                    "x": 1239.2956592956593,
                    "y": 571.17903930131
                },
                {
                    "x": 1244.5372645372645,
                    "y": 547.0742358078603
                }
            ]
        },
        {
            "id": "NhyDE_N09",
            "type": "POLYGON",
            "tags": [
                "jyuc"
            ],
            "boundingBox": {
                "height": 461.1353711790393,
                "width": 579.7215397215398,
                "left": 579.90171990172,
                "top": 374.14847161572055
            },
            "points": [
                {
                    "x": 1158.5749385749386,
                    "y": 743.056768558952
                },
                {
                    "x": 746.5847665847666,
                    "y": 447.51091703056767
                },
                {
                    "x": 701.5069615069615,
                    "y": 411.87772925764193
                },
                {
                    "x": 649.0909090909091,
                    "y": 374.14847161572055
                },
                {
                    "x": 631.2694512694512,
                    "y": 395.10917030567686
                },
                {
                    "x": 614.4963144963145,
                    "y": 418.1659388646288
                },
                {
                    "x": 601.9164619164619,
                    "y": 437.0305676855895
                },
                {
                    "x": 579.90171990172,
                    "y": 471.6157205240175
                },
                {
                    "x": 663.7674037674037,
                    "y": 544.9781659388647
                },
                {
                    "x": 1094.6273546273546,
                    "y": 835.2838427947598
                },
                {
                    "x": 1123.980343980344,
                    "y": 819.5633187772926
                },
                {
                    "x": 1147.0434070434071,
                    "y": 794.410480349345
                },
                {
                    "x": 1159.6232596232596,
                    "y": 765.0655021834061
                }
            ]
        },
        {
            "id": "DO9_mBfI5",
            "type": "POLYGON",
            "tags": [
                "coke"
            ],
            "boundingBox": {
                "height": 307.07423580786025,
                "width": 296.6748566748567,
                "left": 545.3071253071253,
                "top": 530.3056768558952
            },
            "points": [
                {
                    "x": 545.3071253071253,
                    "y": 627.7729257641921
                },
                {
                    "x": 553.6936936936937,
                    "y": 607.8602620087336
                },
                {
                    "x": 579.90171990172,
                    "y": 579.5633187772926
                },
                {
                    "x": 620.7862407862408,
                    "y": 541.8340611353711
                },
                {
                    "x": 641.7526617526618,
                    "y": 530.3056768558952
                },
                {
                    "x": 841.981981981982,
                    "y": 729.4323144104803
                },
                {
                    "x": 839.8853398853399,
                    "y": 742.0087336244542
                },
                {
                    "x": 825.2088452088452,
                    "y": 766.1135371179039
                },
                {
                    "x": 812.6289926289926,
                    "y": 784.9781659388647
                },
                {
                    "x": 799.000819000819,
                    "y": 801.7467248908297
                },
                {
                    "x": 775.9377559377559,
                    "y": 816.4192139737992
                },
                {
                    "x": 756.019656019656,
                    "y": 833.1877729257642
                },
                {
                    "x": 740.2948402948404,
                    "y": 837.3799126637555
                },
                {
                    "x": 548.4520884520884,
                    "y": 637.2052401746724
                }
            ]
        },
        {
            "id": "o61sG72lc",
            "type": "POLYGON",
            "tags": [
                "cup"
            ],
            "boundingBox": {
                "height": 333.27510917030565,
                "width": 204.42260442260442,
                "left": 375.4791154791155,
                "top": 366.8122270742358
            },
            "points": [
                {
                    "x": 402.73546273546276,
                    "y": 558.6026200873363
                },
                {
                    "x": 449.9099099099099,
                    "y": 464.27947598253274
                },
                {
                    "x": 449.9099099099099,
                    "y": 445.414847161572
                },
                {
                    "x": 454.1031941031941,
                    "y": 434.9344978165939
                },
                {
                    "x": 468.7796887796888,
                    "y": 437.0305676855895
                },
                {
                    "x": 464.58640458640457,
                    "y": 417.117903930131
                },
                {
                    "x": 471.9246519246519,
                    "y": 384.6288209606987
                },
                {
                    "x": 481.35954135954137,
                    "y": 366.8122270742358
                },
                {
                    "x": 491.84275184275185,
                    "y": 369.95633187772927
                },
                {
                    "x": 526.4373464373465,
                    "y": 377.29257641921396
                },
                {
                    "x": 555.7903357903358,
                    "y": 387.77292576419217
                },
                {
                    "x": 575.7084357084357,
                    "y": 394.06113537117903
                },
                {
                    "x": 579.90171990172,
                    "y": 399.30131004366814
                },
                {
                    "x": 562.0802620802621,
                    "y": 452.7510917030568
                },
                {
                    "x": 568.3701883701884,
                    "y": 472.6637554585153
                },
                {
                    "x": 562.0802620802621,
                    "y": 480
                },
                {
                    "x": 545.3071253071253,
                    "y": 547.0742358078603
                },
                {
                    "x": 541.1138411138411,
                    "y": 573.2751091703057
                },
                {
                    "x": 548.4520884520884,
                    "y": 585.8515283842795
                },
                {
                    "x": 550.5487305487305,
                    "y": 600.5240174672489
                },
                {
                    "x": 545.3071253071253,
                    "y": 609.9563318777292
                },
                {
                    "x": 545.3071253071253,
                    "y": 622.5327510917031
                },
                {
                    "x": 542.1621621621622,
                    "y": 637.2052401746724
                },
                {
                    "x": 534.8239148239148,
                    "y": 645.589519650655
                },
                {
                    "x": 532.7272727272727,
                    "y": 662.3580786026201
                },
                {
                    "x": 523.2923832923833,
                    "y": 679.1266375545852
                },
                {
                    "x": 526.4373464373465,
                    "y": 694.8471615720524
                },
                {
                    "x": 496.036036036036,
                    "y": 700.0873362445415
                },
                {
                    "x": 471.9246519246519,
                    "y": 696.943231441048
                },
                {
                    "x": 427.8951678951679,
                    "y": 686.4628820960698
                },
                {
                    "x": 404.83210483210485,
                    "y": 679.1266375545852
                },
                {
                    "x": 385.96232596232596,
                    "y": 668.646288209607
                },
                {
                    "x": 377.57575757575756,
                    "y": 653.9737991266376
                },
                {
                    "x": 375.4791154791155,
                    "y": 642.4454148471616
                },
                {
                    "x": 385.96232596232596,
                    "y": 636.1572052401747
                }
            ]
        },
        {
            "id": "PVIrN_RuI",
            "type": "POLYGON",
            "tags": [
                "block"
            ],
            "boundingBox": {
                "height": 193.88646288209608,
                "width": 212.80917280917282,
                "left": 142.75184275184276,
                "top": 303.9301310043668
            },
            "points": [
                {
                    "x": 355.56101556101555,
                    "y": 417.117903930131
                },
                {
                    "x": 282.17854217854216,
                    "y": 303.9301310043668
                },
                {
                    "x": 250.72891072891073,
                    "y": 310.2183406113537
                },
                {
                    "x": 142.75184275184276,
                    "y": 389.86899563318775
                },
                {
                    "x": 221.37592137592137,
                    "y": 497.8165938864629
                },
                {
                    "x": 253.8738738738739,
                    "y": 491.528384279476
                }
            ]
        },
        {
            "id": "HwcW_ao14",
            "type": "POLYGON",
            "tags": [
                "pen_gray"
            ],
            "boundingBox": {
                "height": 313.3624454148472,
                "width": 193.93939393939394,
                "left": 166.86322686322686,
                "top": 469.51965065502185
            },
            "points": [
                {
                    "x": 360.8026208026208,
                    "y": 764.0174672489082
                },
                {
                    "x": 289.5167895167895,
                    "y": 627.7729257641921
                },
                {
                    "x": 294.7583947583948,
                    "y": 625.6768558951965
                },
                {
                    "x": 229.76248976248976,
                    "y": 497.8165938864629
                },
                {
                    "x": 218.23095823095824,
                    "y": 497.8165938864629
                },
                {
                    "x": 199.36117936117935,
                    "y": 469.51965065502185
                },
                {
                    "x": 166.86322686322686,
                    "y": 488.3842794759825
                },
                {
                    "x": 253.8738738738739,
                    "y": 647.6855895196506
                },
                {
                    "x": 261.2121212121212,
                    "y": 646.6375545851529
                },
                {
                    "x": 333.54627354627354,
                    "y": 782.882096069869
                },
                {
                    "x": 349.2710892710893,
                    "y": 774.4978165938865
                }
            ]
        },
        {
            "id": "6MaRykIsL",
            "type": "POLYGON",
            "tags": [
                "brush"
            ],
            "boundingBox": {
                "height": 215.8951965065502,
                "width": 882.8665028665029,
                "left": 0,
                "top": 726.2882096069869
            },
            "points": [
                {
                    "x": 882.8665028665029,
                    "y": 878.2532751091703
                },
                {
                    "x": 869.2383292383292,
                    "y": 866.7248908296943
                },
                {
                    "x": 774.8894348894349,
                    "y": 847.8602620087336
                },
                {
                    "x": 772.7927927927929,
                    "y": 855.1965065502184
                },
                {
                    "x": 764.4062244062244,
                    "y": 883.4934497816594
                },
                {
                    "x": 751.8263718263719,
                    "y": 891.8777292576419
                },
                {
                    "x": 740.2948402948404,
                    "y": 888.7336244541485
                },
                {
                    "x": 665.8640458640459,
                    "y": 880.349344978166
                },
                {
                    "x": 626.0278460278461,
                    "y": 869.8689956331878
                },
                {
                    "x": 557.8869778869779,
                    "y": 852.0524017467249
                },
                {
                    "x": 519.0990990990991,
                    "y": 835.2838427947598
                },
                {
                    "x": 499.1809991809992,
                    "y": 830.0436681222708
                },
                {
                    "x": 479.2628992628993,
                    "y": 818.5152838427948
                },
                {
                    "x": 465.6347256347256,
                    "y": 819.5633187772926
                },
                {
                    "x": 442.57166257166256,
                    "y": 813.2751091703057
                },
                {
                    "x": 411.1220311220311,
                    "y": 800.6986899563319
                },
                {
                    "x": 339.83619983619985,
                    "y": 782.882096069869
                },
                {
                    "x": 331.44963144963145,
                    "y": 783.9301310043668
                },
                {
                    "x": 325.15970515970514,
                    "y": 777.6419213973799
                },
                {
                    "x": 273.7919737919738,
                    "y": 769.2576419213974
                },
                {
                    "x": 230.8108108108108,
                    "y": 756.6812227074236
                },
                {
                    "x": 180.4914004914005,
                    "y": 747.2489082969432
                },
                {
                    "x": 143.8001638001638,
                    "y": 742.0087336244542
                },
                {
                    "x": 103.96396396396396,
                    "y": 734.6724890829694
                },
                {
                    "x": 80.90090090090091,
                    "y": 732.5764192139738
                },
                {
                    "x": 48.402948402948404,
                    "y": 732.5764192139738
                },
                {
                    "x": 15.904995904995905,
                    "y": 726.2882096069869
                },
                {
                    "x": 5.4217854217854216,
                    "y": 734.6724890829694
                },
                {
                    "x": 0,
                    "y": 743.056768558952
                },
                {
                    "x": 0,
                    "y": 772.4017467248908
                },
                {
                    "x": 48.402948402948404,
                    "y": 776.5938864628821
                },
                {
                    "x": 137.51023751023752,
                    "y": 788.1222707423581
                },
                {
                    "x": 221.37592137592137,
                    "y": 809.0829694323144
                },
                {
                    "x": 307.33824733824736,
                    "y": 827.9475982532751
                },
                {
                    "x": 412.1703521703522,
                    "y": 856.2445414847161
                },
                {
                    "x": 477.1662571662572,
                    "y": 870.9170305676856
                },
                {
                    "x": 489.74610974610977,
                    "y": 880.349344978166
                },
                {
                    "x": 546.3554463554464,
                    "y": 885.589519650655
                },
                {
                    "x": 676.3472563472563,
                    "y": 906.5502183406113
                },
                {
                    "x": 742.3914823914824,
                    "y": 917.0305676855895
                },
                {
                    "x": 757.067977067977,
                    "y": 923.3187772925764
                },
                {
                    "x": 794.8075348075348,
                    "y": 933.7991266375545
                },
                {
                    "x": 857.7067977067977,
                    "y": 940.0873362445415
                },
                {
                    "x": 873.4316134316134,
                    "y": 942.1834061135371
                },
                {
                    "x": 876.5765765765766,
                    "y": 920.1746724890829
                }
            ]
        }
    ],
    "version": "2.2.0"
}